python_invest/__init__.py
python_invest/cli/__init__.py
python_invest/cli/cli.py
python_invest/const.py
python_invest/invest/__init__.py
python_invest/invest/crypto.py
python_invest/invest/firebase.py
python_invest/invest/founds.py
python_invest/invest/main.py
python_invest/invest/stocks.py
python_invest/invest/utils.py
python_invest/invest/validators.py
python_invest-0.2.0.dist-info/LICENSE
python_invest-0.2.0.dist-info/WHEEL
python_invest-0.2.0.dist-info/METADATA
python_invest-0.2.0.dist-info/RECORD
