Metadata-Version: 2.1
Name: python-invest
Version: 0.2.0
Summary: Package to financial data extraction with Python.
Author: Claudio Lima
Author-email: clcostaf@hotmail.com
Requires-Python: >=3.10,<4.0
Classifier: Programming Language :: Python :: 3
Classifier: Programming Language :: Python :: 3.10
Requires-Dist: httpx (>=0.23.3,<0.24.0)
Requires-Dist: pandas (>=1.5.3,<2.0.0)
Project-URL: Documentation, https://pyinvest.readthedocs.io/en/latest/
Project-URL: GitHub, https://github.com/clcosta/python-invest
